gileum_server/__init__.py
gileum_server/gunicorn.py
gileum_server/hypercorn.py
gileum_server/types.py
tests/__init__.py
gileum_server-0.0.1.dist-info/LICENCE
gileum_server-0.0.1.dist-info/METADATA
gileum_server-0.0.1.dist-info/WHEEL
gileum_server-0.0.1.dist-info/top_level.txt
gileum_server-0.0.1.dist-info/RECORD
