Metadata-Version: 2.1
Name: gileum-server
Version: 0.0.1
Summary: UNKNOWN
Home-page: UNKNOWN
Author: Yunhyeon Jeong
Author-email: jjj999to@gmail.com
License: UNKNOWN
Platform: UNKNOWN
Requires-Dist: gileum
Requires-Dist: gunicorn
Requires-Dist: hypercorn
